LICENSE
MANIFEST.in
README.md
setup.cfg
setup.py
cocotbext/dvi/__init__.py
cocotbext/dvi/cocotbext_logger.py
cocotbext/dvi/diffclock.py
cocotbext/dvi/diffobject.py
cocotbext/dvi/dvi_bus.py
cocotbext/dvi/dvi_driver.py
cocotbext/dvi/dvi_sink.py
cocotbext/dvi/rgb_bus.py
cocotbext/dvi/rgb_driver.py
cocotbext/dvi/rgb_sink.py
cocotbext/dvi/rgbimage.py
cocotbext/dvi/sigorvar.py
cocotbext/dvi/sync_driver.py
cocotbext/dvi/tmds.py
cocotbext/dvi/version.py
cocotbext_dvi.egg-info/PKG-INFO
cocotbext_dvi.egg-info/SOURCES.txt
cocotbext_dvi.egg-info/dependency_links.txt
cocotbext_dvi.egg-info/requires.txt
cocotbext_dvi.egg-info/top_level.txt
tests/dvi/Makefile
tests/dvi/test_dut.py
tests/dvi/test_dut_001.py
tests/test_rgb2dvi/Makefile
tests/test_rgb2dvi/test_dut.py
tests/test_verilog/Makefile
tests/test_verilog/test_dut.py
tests/test_vhdl/Makefile
tests/test_vhdl/test_dut.py