Metadata-Version: 2.1
Name: cocotbext-dvi
Version: 0.5.0
Summary: DVI and RGB modules for cocotb
Home-page: https://github.com/daxzio/cocotbext-dvi
Download-URL: https://github.com/daxzio/cocotbext-dvi/tarball/master
Author: Dave Keeshan
Author-email: dave.keeshan@daxzio.com
License: MIT
Project-URL: Bug Tracker, https://github.com/daxzio/cocotbext-dvi/issues
Project-URL: Source Code, https://github.com/daxzio/cocotbext-dvi
Keywords: dvi,cocotb
Platform: any
Classifier: Development Status :: 3 - Alpha
Classifier: Framework :: cocotb
Classifier: License :: OSI Approved :: MIT License
Classifier: Operating System :: OS Independent
Classifier: Programming Language :: Python :: 3
Classifier: Topic :: Scientific/Engineering :: Electronic Design Automation (EDA)
Requires-Python: >=3.8
Provides-Extra: test
License-File: LICENSE
